flyteplugins/ray/__init__.py
flyteplugins/ray/task.py
flyteplugins_ray-2.0.0b53.dist-info/METADATA
flyteplugins_ray-2.0.0b53.dist-info/WHEEL
flyteplugins_ray-2.0.0b53.dist-info/top_level.txt
flyteplugins_ray-2.0.0b53.dist-info/RECORD
