Metadata-Version: 2.4
Name: flyteplugins-ray
Version: 2.0.0b53
Summary: Ray plugin for flyte
Author-email: Kevin Su <pingsutw@users.noreply.github.com>
Requires-Python: <3.13,>=3.10
Requires-Dist: ray[default]
Requires-Dist: flyte
